[
  {
    "name": "Mereba",
    "id": 144213,
    "instagram_name": "mereba",
    "alternate_names": [
      "M. Mereba",
      "Marian Mereba"
    ],
    "description": {
      "plain": "Marian Mereba (b. September 19, 1987), known mononymously as Mereba, is a singer, songwriter, and producer based between Atlanta and Los Angeles. She is known for frequent collaborations with members of the Atlanta-based collective, Spillage Village.\n\nAfter years of singles and EPs, she released her debut album, The Jungle Is the Only Way Out, on February 27, 2019."
    },
    "image_url": "https://images.genius.com/e2ca3fe77c65059322789765fc565e5d.1000x1000x1.jpg"
  }
]